{
 "а": 1,
 "ага": 3,
 "алли": 4,
 "б": 1,
 "бадди": 5,
 "балдеешь": 8,
 "балдел": 6,
 "балдеют": 7,
 "бар": 3,
 "бассейна": 8,
 "бегает": 6,
 "бегал": 5,
 "беда": 4,
 "без": 3,
 "безобразно": 10,
 "белые": 5,
 "белым": 5,
 "бернис": 6,
 "беспокоился": 11,
 "блестящий": 9,
 "близко": 6,
 "блондинка": 9,
 "блондинке": 9,
 "блондинки": 9,
 "блондинку": 9,
 "блондинок": 9,
 "бобби": 5,
 "бог": 3,
 "богу": 4,
 "боже": 4,
 "большая": 7,
 "больше": 6,
 "большеротая": 11,
 "большого": 8,
 "боялся": 6,
 "боятся": 6,
 "брал": 4,
 "брали": 5,
 "брат": 4,
 "брата": 5,
 "братишка": 8,
 "брать": 5,
 "брови": 5,
 "будет": 5,
 "будете": 6,
 "будто": 5,
 "бы": 2,
 "бывает": 6,
 "бывало": 6,
 "был": 3,
 "была": 4,
 "были": 4,
 "было": 4,
 "быстрая": 7,
 "быстро": 6,
 "быструю": 7,
 "быстрый": 7,
 "быть": 4,
 "бьешь": 5,
 "бэнки": 5,
 "в": 1,
 "важная": 6,
 "вам": 3,
 "ванную": 6,
 "вас": 3,
 "вашему": 6,
 "вашингтон": 9,
 "ввалится": 8,
 "вверх": 5,
 "вдруг": 5,
 "ведра": 5,
 "ведь": 4,
 "ведьм": 5,
 "вежливо": 7,
 "везти": 5,
 "велел": 5,
 "веранда": 7,
 "веранде": 7,
 "веранду": 7,
 "вернее": 6,
 "вернулись": 9,
 "вернуться": 9,
 "вертелся": 8,
 "вертят": 6,
 "весной": 6,
 "вести": 5,
 "весь": 4,
 "вечера": 6,
 "вечером": 7,
 "вечно": 5,
 "вещей": 5,
 "вещь": 4,
 "взглядом": 8,
 "взором": 6,
 "взял": 4,
 "вид": 3,
 "видела": 6,
 "видели": 6,
 "видите": 6,
 "видишь": 6,
 "видно": 5,
 "вижу": 4,
 "вилледж": 7,
 "виноват": 7,
 "виски": 5,
 "влюбился": 8,
 "влюбляюсь": 9,
 "вместе": 6,
 "вмешивалась": 11,
 "внимания": 8,
 "во": 2,
 "вовсе": 5,
 "водили": 6,
 "водителем": 9,
 "возьмемся": 9,
 "возьми": 6,
 "вокруг": 6,
 "волновалась": 11,
 "волосы": 6,
 "вон": 3,
 "воняло": 6,
 "воображала": 10,
 "вообще": 6,
 "восемь": 6,
 "воскресеньям": 12,
 "вот": 3,
 "впрочем": 7,
 "время": 5,
 "вроде": 5,
 "вряд": 4,
 "все": 3,
 "всегда": 6,
 "всего": 5,
 "всем": 4,
 "всеми": 5,
 "всерьез": 7,
 "всполошились": 12,
 "вспоминать": 10,
 "вспомнил": 8,
 "вспомню": 7,
 "вставать": 8,
 "встал": 5,
 "встала": 6,
 "встали": 6,
 "встать": 6,
 "встречал": 8,
 "встречала": 9,
 "всю": 3,
 "всякие": 6,
 "всякий": 6,
 "всяком": 6,
 "вторая": 6,
 "вторых": 6,
 "вчера": 5,
 "вы": 2,
 "выбросить": 9,
 "выводила": 8,
 "выглядит": 8,
 "выглянул": 8,
 "выкинуть": 8,
 "вымылся": 7,
 "вынести": 7,
 "вынул": 5,
 "выпили": 6,
 "выражайтесь": 11,
 "высидеть": 8,
 "высокий": 7,
 "выставляться": 12,
 "высшей": 6,
 "вытворяют": 9,
 "вытурили": 8,
 "выхода": 6,
 "выходя": 6,
 "вышел": 5,
 "вышли": 5,
 "вышло": 5,
 "гадил": 5,
 "гадит": 5,
 "газету": 6,
 "галлахер": 8,
 "где": 3,
 "гиены": 5,
 "гизела": 6,
 "главным": 7,
 "гладит": 6,
 "гладят": 6,
 "глажу": 5,
 "глаз": 4,
 "глаза": 5,
 "глазеет": 7,
 "глазел": 6,
 "глазки": 6,
 "глупее": 6,
 "глупостей": 9,
 "глупости": 8,
 "глупы": 5,
 "гнусный": 7,
 "говорил": 7,
 "говорила": 8,
 "говорили": 8,
 "говорит": 7,
 "говорить": 8,
 "говоришь": 8,
 "говорю": 6,
 "говоря": 6,
 "говорят": 7,
 "гогочет": 7,
 "гогочут": 7,
 "голливуд": 8,
 "голове": 6,
 "головой": 7,
 "головы": 6,
 "голос": 5,
 "голосу": 6,
 "гольф": 5,
 "гораздо": 7,
 "горвиц": 6,
 "горя": 4,
 "господи": 7,
 "гостинице": 9,
 "гостиную": 8,
 "грех": 4,
 "гринич": 6,
 "громадный": 9,
 "громкий": 7,
 "громко": 6,
 "грузовике": 9,
 "губы": 4,
 "гэри": 4,
 "да": 2,
 "давайте": 7,
 "давать": 6,
 "давно": 5,
 "дадут": 5,
 "даже": 4,
 "дайте": 5,
 "дали": 4,
 "дама": 4,
 "дамами": 6,
 "дамки": 5,
 "дамы": 4,
 "дб": 2,
 "двадцати": 8,
 "две": 3,
 "двенадцать": 10,
 "девается": 8,
 "деваются": 8,
 "девицами": 8,
 "девицы": 6,
 "девочку": 7,
 "девушка": 7,
 "девушки": 7,
 "девчонка": 8,
 "девчонками": 10,
 "девчонки": 8,
 "девчонкой": 9,
 "девчонок": 8,
 "девять": 6,
 "действует": 9,
 "декабре": 7,
 "делает": 6,
 "делается": 8,
 "делают": 6,
 "деле": 4,
 "дело": 4,
 "день": 4,
 "деньги": 6,
 "держались": 9,
 "держаться": 9,
 "держишься": 9,
 "держу": 5,
 "десять": 6,
 "детски": 6,
 "джейн": 5,
 "джентльмен": 10,
 "джим": 4,
 "джиттербаг": 10,
 "диалог": 6,
 "для": 3,
 "дней": 4,
 "до": 2,
 "доберман": 8,
 "добился": 7,
 "добиться": 8,
 "довольно": 8,
 "догадывается": 12,
 "дождь": 5,
 "доказывал": 9,
 "долго": 5,
 "доллар": 6,
 "долларов": 8,
 "дом": 3,
 "доме": 4,
 "домой": 5,
 "донат": 5,
 "донатом": 7,
 "донату": 6,
 "допили": 6,
 "дороге": 6,
 "досадно": 7,
 "доски": 5,
 "доску": 5,
 "дотронешься": 11,
 "доходит": 7,
 "дразнил": 7,
 "дразнила": 8,
 "дразнить": 8,
 "друг": 4,
 "другая": 6,
 "другие": 6,
 "другими": 7,
 "других": 6,
 "другой": 6,
 "другом": 6,
 "другую": 6,
 "дрянное": 7,
 "дрянной": 7,
 "дудочкой": 8,
 "дула": 4,
 "думаем": 6,
 "думайте": 7,
 "думал": 5,
 "думали": 6,
 "думать": 6,
 "думаю": 5,
 "дур": 3,
 "дура": 4,
 "дурак": 5,
 "дурацкую": 8,
 "дурища": 6,
 "дурой": 5,
 "дуру": 4,
 "дуры": 4,
 "душе": 4,
 "души": 4,
 "душкой": 6,
 "дьявольски": 10,
 "его": 3,
 "единственный": 12,
 "едите": 5,
 "ее": 2,
 "ежели": 5,
 "ездила": 6,
 "езжу": 4,
 "ей": 2,
 "еле": 3,
 "ему": 3,
 "ерунда": 6,
 "если": 4,
 "есть": 4,
 "ехал": 4,
 "еще": 3,
 "жалкие": 6,
 "жалко": 5,
 "ждет": 4,
 "ждут": 4,
 "же": 2,
 "жена": 4,
 "жениться": 8,
 "женщины": 7,
 "живет": 5,
 "живого": 6,
 "животе": 6,
 "жизни": 5,
 "за": 2,
 "забавное": 8,
 "забудем": 7,
 "забываешь": 9,
 "завести": 7,
 "заволновалась": 13,
 "завтра": 6,
 "заговаривать": 12,
 "задается": 8,
 "задворках": 9,
 "задик": 5,
 "заиграл": 7,
 "заказал": 7,
 "заказать": 8,
 "закатились": 10,
 "закладывает": 11,
 "законно": 7,
 "закружил": 8,
 "закрывала": 9,
 "закрывался": 10,
 "зал": 3,
 "зала": 4,
 "зале": 4,
 "залу": 4,
 "замечательно": 12,
 "замолчать": 9,
 "замучился": 9,
 "заорет": 6,
 "заплатят": 8,
 "заплетает": 9,
 "запродался": 10,
 "заставил": 8,
 "заставить": 9,
 "заставлен": 9,
 "застекленная": 12,
 "захихикали": 10,
 "захотели": 8,
 "захотелось": 10,
 "зачем": 5,
 "звали": 5,
 "звонить": 7,
 "здесь": 5,
 "здоровались": 11,
 "здорово": 7,
 "зимой": 5,
 "знает": 5,
 "знаете": 6,
 "знаком": 6,
 "знал": 4,
 "знала": 5,
 "знаменитость": 12,
 "знать": 5,
 "значит": 6,
 "знаю": 4,
 "зовут": 5,
 "и": 1,
 "игра": 4,
 "играет": 6,
 "играл": 5,
 "играла": 6,
 "играли": 6,
 "играть": 6,
 "играю": 5,
 "игре": 4,
 "игру": 4,
 "идет": 4,
 "идиотка": 7,
 "идиотки": 7,
 "идут": 4,
 "из": 2,
 "известно": 8,
 "извиняться": 10,
 "изводить": 8,
 "или": 3,
 "им": 2,
 "имени": 5,
 "иначе": 5,
 "иногда": 6,
 "интересно": 9,
 "интуиция": 8,
 "искали": 6,
 "искать": 6,
 "исписанную": 10,
 "испортилось": 11,
 "испортить": 9,
 "истерике": 8,
 "исчезли": 7,
 "их": 2,
 "йорк": 4,
 "йорке": 5,
 "к": 1,
 "кабак": 5,
 "кабака": 6,
 "каждая": 6,
 "каждое": 6,
 "казалась": 8,
 "казалось": 8,
 "как": 3,
 "какая": 5,
 "какие": 5,
 "каким": 5,
 "каких": 5,
 "какого": 6,
 "какое": 5,
 "какую": 5,
 "капельку": 8,
 "капнула": 7,
 "картина": 7,
 "картину": 7,
 "катаются": 8,
 "кем": 3,
 "кино": 4,
 "киноактера": 10,
 "киноартист": 10,
 "киноартистов": 12,
 "кинозвезд": 9,
 "кинозвезды": 10,
 "кинохроника": 11,
 "кисела": 6,
 "кларнет": 7,
 "кларнетиста": 11,
 "классе": 6,
 "клуб": 4,
 "клуба": 5,
 "клубе": 5,
 "книжки": 6,
 "ко": 2,
 "когда": 5,
 "кого": 4,
 "код": 3,
 "кожи": 4,
 "кока": 4,
 "колдун": 6,
 "колени": 6,
 "колу": 4,
 "колы": 4,
 "комнату": 7,
 "компания": 8,
 "конечно": 7,
 "конце": 5,
 "концов": 6,
 "кончаю": 6,
 "кончится": 8,
 "коньках": 7,
 "коньков": 7,
 "королева": 8,
 "коротенькие": 11,
 "короткометражки": 15,
 "которого": 8,
 "которой": 7,
 "котором": 7,
 "который": 7,
 "которым": 7,
 "которых": 7,
 "крабс": 5,
 "красавица": 9,
 "красиво": 7,
 "красивые": 8,
 "красное": 7,
 "красному": 8,
 "красный": 7,
 "кребс": 5,
 "кресле": 6,
 "кресло": 6,
 "кроме": 5,
 "крошка": 6,
 "кругов": 6,
 "кругом": 6,
 "крупно": 6,
 "крутилась": 9,
 "кто": 3,
 "куда": 4,
 "купер": 5,
 "кюдехи": 6,
 "лаверн": 6,
 "ладно": 5,
 "ладонь": 6,
 "ласково": 7,
 "легкая": 6,
 "легко": 5,
 "лед": 3,
 "леди": 4,
 "ледышка": 7,
 "ледяным": 7,
 "лежала": 6,
 "лез": 3,
 "лет": 3,
 "лето": 4,
 "летом": 5,
 "ли": 2,
 "либо": 4,
 "лил": 3,
 "лифте": 5,
 "лицо": 4,
 "лишь": 4,
 "лоб": 3,
 "лодка": 5,
 "ложиться": 8,
 "лорре": 5,
 "лошадь": 6,
 "лучше": 5,
 "лучшей": 6,
 "любил": 5,
 "любила": 6,
 "любимый": 7,
 "люблю": 5,
 "люди": 4,
 "макушку": 7,
 "маленькая": 9,
 "маленькие": 9,
 "маленькое": 9,
 "мало": 4,
 "мама": 4,
 "маме": 4,
 "марко": 5,
 "марокко": 7,
 "марти": 5,
 "матери": 6,
 "матерью": 7,
 "мать": 4,
 "машине": 6,
 "между": 5,
 "мейне": 5,
 "мельком": 7,
 "меня": 4,
 "мертвая": 7,
 "места": 5,
 "местах": 6,
 "месте": 5,
 "местечко": 8,
 "мизинец": 7,
 "мило": 4,
 "миль": 4,
 "мимо": 4,
 "минуту": 6,
 "миранду": 7,
 "мистер": 6,
 "мне": 3,
 "мнешься": 7,
 "много": 5,
 "мной": 4,
 "мог": 3,
 "могли": 5,
 "могу": 4,
 "могут": 5,
 "моей": 4,
 "моему": 5,
 "может": 5,
 "можете": 6,
 "можно": 5,
 "моих": 4,
 "мой": 3,
 "молод": 5,
 "молчала": 7,
 "мою": 3,
 "моя": 3,
 "муж": 3,
 "мужа": 4,
 "музыка": 6,
 "мы": 2,
 "мыс": 3,
 "мюзик": 5,
 "мямлишь": 7,
 "мячей": 5,
 "мячу": 4,
 "на": 2,
 "наверно": 7,
 "наверняка": 9,
 "надел": 5,
 "надела": 6,
 "наделал": 7,
 "наденет": 7,
 "надо": 4,
 "надоест": 7,
 "надул": 5,
 "назвала": 7,
 "называла": 8,
 "назывался": 9,
 "наизусть": 8,
 "наклонился": 10,
 "накрученные": 11,
 "нам": 3,
 "нами": 4,
 "наоборот": 8,
 "напиваться": 10,
 "напиться": 8,
 "наплевать": 9,
 "напоказ": 7,
 "напомнит": 8,
 "например": 8,
 "нарочно": 7,
 "нас": 3,
 "насквозь": 8,
 "настоящая": 9,
 "настоящему": 10,
 "настоящий": 9,
 "настроение": 10,
 "натренировал": 12,
 "научил": 6,
 "начал": 5,
 "начать": 6,
 "начинала": 8,
 "наш": 3,
 "наша": 4,
 "нашего": 6,
 "нашей": 5,
 "нашу": 4,
 "не": 2,
 "невнятное": 9,
 "невозможно": 10,
 "невозможным": 11,
 "невоспитанности": 15,
 "него": 4,
 "негр": 4,
 "нее": 3,
 "ней": 3,
 "некрасивых": 10,
 "нельзя": 6,
 "немецкий": 8,
 "немножко": 8,
 "нему": 4,
 "ненавидеть": 10,
 "ненавижу": 8,
 "непременно": 10,
 "нервы": 5,
 "несколько": 9,
 "несла": 5,
 "несовершеннолетнего": 19,
 "несовершеннолетнему": 19,
 "несовершеннолетний": 18,
 "несчастью": 9,
 "нет": 3,
 "нечего": 6,
 "ни": 2,
 "нибудь": 6,
 "нигде": 5,
 "никак": 5,
 "никакой": 7,
 "никогда": 7,
 "никого": 6,
 "никто": 5,
 "никуда": 6,
 "ним": 3,
 "ними": 4,
 "них": 3,
 "ничего": 6,
 "ничуть": 6,
 "но": 2,
 "ноги": 4,
 "номер": 5,
 "норовит": 7,
 "нос": 3,
 "ночной": 6,
 "ночью": 5,
 "нравилась": 9,
 "нравилось": 9,
 "нравится": 8,
 "ну": 2,
 "нужно": 5,
 "нью": 3,
 "о": 1,
 "об": 2,
 "обалдел": 7,
 "обалдела": 8,
 "обалдеть": 8,
 "обдала": 6,
 "обдать": 6,
 "обдумывает": 10,
 "обеда": 5,
 "обернется": 9,
 "обернулся": 9,
 "обиделась": 9,
 "обиделись": 9,
 "обиделся": 8,
 "обижается": 9,
 "обижайтесь": 10,
 "облезлого": 9,
 "обманывать": 10,
 "обнимались": 10,
 "обнявшись": 9,
 "образом": 7,
 "обращала": 8,
 "обращаюсь": 9,
 "общем": 5,
 "обществе": 8,
 "объяснить": 9,
 "обычно": 6,
 "оголтелый": 9,
 "огромная": 8,
 "один": 4,
 "одиноко": 7,
 "одна": 4,
 "одно": 4,
 "одной": 5,
 "одном": 5,
 "одну": 4,
 "одолжение": 9,
 "озерцо": 6,
 "озиралась": 9,
 "озирались": 9,
 "озираются": 9,
 "оказалось": 9,
 "оказывается": 11,
 "окинул": 6,
 "окно": 4,
 "около": 5,
 "он": 2,
 "она": 3,
 "они": 3,
 "опять": 5,
 "оркестр": 7,
 "оркестра": 8,
 "оскорбил": 8,
 "особа": 5,
 "особенно": 8,
 "остается": 8,
 "остановилась": 12,
 "остаются": 8,
 "остроумная": 10,
 "остроумно": 9,
 "от": 2,
 "ответила": 8,
 "ответим": 7,
 "отвечает": 8,
 "отвечайте": 9,
 "отвечать": 8,
 "отводила": 8,
 "отвратительный": 14,
 "отец": 4,
 "открывать": 9,
 "открыл": 6,
 "откуда": 6,
 "отличная": 8,
 "отлично": 7,
 "отличные": 8,
 "отметки": 7,
 "относятся": 9,
 "отпускают": 9,
 "отсюда": 6,
 "оттого": 6,
 "отыщу": 5,
 "официант": 8,
 "официанту": 9,
 "ох": 2,
 "очень": 5,
 "очереди": 7,
 "очумел": 6,
 "палисадник": 10,
 "пальто": 6,
 "пальцем": 7,
 "папа": 4,
 "папе": 4,
 "пара": 4,
 "парк": 4,
 "парке": 5,
 "парусная": 8,
 "пекаря": 6,
 "первого": 7,
 "первое": 6,
 "первый": 6,
 "первых": 6,
 "перевернуть": 11,
 "передумал": 9,
 "переживает": 10,
 "переодевался": 12,
 "переоделся": 10,
 "переспрашивает": 14,
 "переспросила": 12,
 "перестал": 8,
 "перетанцевал": 12,
 "переходила": 10,
 "перчатки": 8,
 "пила": 4,
 "пили": 4,
 "пинчер": 6,
 "писатель": 8,
 "питер": 5,
 "питера": 6,
 "пишет": 5,
 "плавают": 7,
 "плакала": 7,
 "платить": 7,
 "плоха": 5,
 "плохая": 6,
 "плохих": 6,
 "плохо": 5,
 "плохую": 6,
 "площадку": 8,
 "по": 2,
 "побери": 6,
 "поболтать": 9,
 "поведешь": 8,
 "повезло": 7,
 "повели": 6,
 "поверили": 8,
 "повесить": 8,
 "повторять": 9,
 "повторяю": 8,
 "поганое": 7,
 "поганом": 7,
 "поглядывать": 11,
 "поговорить": 10,
 "под": 3,
 "подает": 6,
 "подали": 6,
 "подаст": 6,
 "подбавить": 9,
 "подвернется": 11,
 "поддразнивал": 12,
 "подлого": 7,
 "подлым": 6,
 "поднимать": 9,
 "подняла": 7,
 "подобного": 9,
 "подойдут": 8,
 "подошел": 7,
 "подошла": 7,
 "подошли": 7,
 "подписывает": 11,
 "подразнили": 10,
 "подрал": 6,
 "подругам": 8,
 "подругами": 9,
 "подружились": 11,
 "подружиться": 11,
 "подсел": 6,
 "подумайте": 9,
 "подумал": 7,
 "подумать": 8,
 "подъезжает": 10,
 "подымает": 8,
 "пожалуйста": 10,
 "позвал": 6,
 "позволила": 9,
 "позвонила": 9,
 "позвонить": 9,
 "поздно": 6,
 "поздоровался": 12,
 "познакомились": 13,
 "познакомился": 12,
 "пойдемте": 8,
 "пойду": 5,
 "пойти": 5,
 "пока": 4,
 "показывает": 10,
 "показывал": 9,
 "покончили": 9,
 "покупал": 7,
 "полагается": 10,
 "поле": 4,
 "полисменов": 10,
 "полю": 4,
 "помню": 5,
 "помолчал": 8,
 "понимает": 8,
 "понимаете": 9,
 "понимала": 8,
 "понимали": 8,
 "понимаю": 7,
 "понравилась": 11,
 "поняла": 6,
 "поняли": 6,
 "понятно": 7,
 "попадаются": 10,
 "попаду": 6,
 "попало": 6,
 "попасть": 7,
 "попробовал": 10,
 "попросил": 8,
 "попрощаться": 11,
 "пор": 3,
 "пора": 4,
 "пороть": 6,
 "портить": 7,
 "поручился": 9,
 "порции": 6,
 "поселке": 7,
 "посетители": 10,
 "посидеть": 8,
 "после": 5,
 "последнего": 10,
 "последнюю": 9,
 "посматривать": 12,
 "посмотрел": 9,
 "посмотрели": 10,
 "посмотреть": 10,
 "посмотрю": 8,
 "поступила": 9,
 "потанцевать": 11,
 "потанцуем": 9,
 "потеет": 6,
 "потеряла": 8,
 "потерять": 8,
 "потесниться": 11,
 "потом": 5,
 "потому": 6,
 "потрепаться": 11,
 "похож": 5,
 "похожей": 7,
 "поцеловал": 9,
 "поцеловались": 12,
 "почем": 5,
 "почему": 6,
 "почти": 5,
 "почувствовал": 12,
 "почувствовать": 13,
 "пошел": 5,
 "пошла": 5,
 "пошли": 5,
 "пошлятину": 9,
 "пошлячка": 8,
 "появляется": 10,
 "права": 5,
 "правда": 6,
 "правде": 6,
 "предложить": 10,
 "представить": 11,
 "прежде": 6,
 "презрением": 10,
 "прелесть": 8,
 "при": 3,
 "привлекательный": 15,
 "привязчива": 10,
 "пригласили": 10,
 "придем": 6,
 "придираться": 11,
 "придумать": 9,
 "приезжают": 9,
 "приезжие": 8,
 "приехала": 8,
 "приехали": 8,
 "приоткрыт": 9,
 "пристает": 8,
 "пристойно": 9,
 "пришлось": 8,
 "приятно": 7,
 "про": 3,
 "пробор": 6,
 "проводила": 9,
 "программу": 9,
 "проезжали": 9,
 "прозевали": 9,
 "пройдет": 7,
 "проклятый": 9,
 "промерзнет": 10,
 "пропищал": 8,
 "пропойца": 8,
 "просил": 6,
 "просила": 7,
 "простите": 8,
 "просто": 6,
 "противно": 8,
 "профессионалкой": 15,
 "профессиональной": 16,
 "профессор": 9,
 "прохладительное": 15,
 "прошу": 5,
 "пруд": 4,
 "пруда": 5,
 "пруду": 5,
 "прямо": 5,
 "прячется": 8,
 "психи": 5,
 "пускать": 7,
 "пусто": 5,
 "пусть": 5,
 "пью": 3,
 "пьяница": 7,
 "работа": 6,
 "работали": 8,
 "работают": 8,
 "работу": 6,
 "равно": 5,
 "равнодушным": 11,
 "радио": 5,
 "раз": 3,
 "раза": 4,
 "разбавлять": 10,
 "разбирал": 8,
 "разве": 5,
 "разговаривал": 12,
 "разговаривали": 13,
 "разговаривать": 13,
 "разговор": 8,
 "разговорился": 12,
 "раздражает": 10,
 "раздражало": 10,
 "раздражительный": 15,
 "размазала": 9,
 "разнимаем": 9,
 "разница": 7,
 "разницы": 7,
 "разрешил": 8,
 "разумеется": 10,
 "раймю": 5,
 "рано": 4,
 "раньше": 6,
 "расплакалась": 12,
 "распоряжение": 12,
 "рассказывал": 11,
 "рассказывать": 12,
 "расстроились": 12,
 "расстроился": 11,
 "расфуфыренные": 13,
 "ребенка": 7,
 "ревела": 6,
 "редко": 5,
 "решил": 5,
 "решили": 6,
 "рисковать": 9,
 "робертом": 8,
 "роберту": 7,
 "родители": 8,
 "родных": 6,
 "рома": 4,
 "роста": 5,
 "рот": 3,
 "рояле": 5,
 "рояль": 5,
 "рубашку": 7,
 "рук": 3,
 "рука": 4,
 "рукавицу": 8,
 "руки": 4,
 "рукой": 5,
 "руку": 4,
 "рыбам": 5,
 "рыбы": 4,
 "рыжие": 5,
 "рынок": 5,
 "рюмок": 5,
 "ряда": 4,
 "рядом": 5,
 "с": 1,
 "сам": 3,
 "сама": 4,
 "самая": 5,
 "сами": 4,
 "самом": 5,
 "самый": 5,
 "сверстников": 11,
 "свести": 6,
 "свет": 4,
 "света": 5,
 "свете": 5,
 "светским": 8,
 "свеч": 4,
 "свидание": 8,
 "свитер": 6,
 "свободен": 8,
 "свободы": 7,
 "своего": 6,
 "своей": 5,
 "своем": 5,
 "своим": 5,
 "своими": 6,
 "свой": 4,
 "сволочь": 7,
 "свою": 4,
 "свысока": 7,
 "свяжешься": 9,
 "сделала": 7,
 "сделали": 7,
 "сделать": 7,
 "сеанс": 5,
 "себе": 4,
 "себя": 4,
 "сегодня": 7,
 "сейчас": 6,
 "сел": 3,
 "селедку": 7,
 "семье": 5,
 "сердится": 8,
 "сестренка": 9,
 "сестренке": 9,
 "сестренкой": 10,
 "сестренку": 9,
 "сестры": 6,
 "сесть": 5,
 "сигаретами": 10,
 "сигареты": 8,
 "сидел": 5,
 "сидела": 6,
 "сидели": 6,
 "сидеть": 6,
 "сидят": 5,
 "силком": 6,
 "сингер": 6,
 "сингера": 7,
 "сиреневого": 10,
 "сиреневом": 9,
 "сиреневый": 9,
 "сирота": 6,
 "сити": 4,
 "сиэтла": 6,
 "сиэтле": 6,
 "скажет": 6,
 "скажешь": 7,
 "сказал": 6,
 "сказала": 7,
 "сказать": 7,
 "скакать": 7,
 "скверно": 7,
 "складная": 8,
 "сколько": 7,
 "скучно": 6,
 "следует": 7,
 "слез": 4,
 "слеза": 5,
 "слезу": 5,
 "слишком": 7,
 "слово": 5,
 "словом": 6,
 "случае": 6,
 "случай": 6,
 "случайно": 8,
 "случилось": 9,
 "слушает": 7,
 "слушайте": 8,
 "слушала": 7,
 "слушалась": 9,
 "слушать": 7,
 "слушьте": 7,
 "слыхала": 7,
 "слыхали": 7,
 "слышно": 6,
 "смертельно": 10,
 "смертный": 8,
 "смех": 4,
 "смешная": 7,
 "смешнее": 7,
 "смешно": 6,
 "смешного": 8,
 "смогли": 6,
 "смотрел": 7,
 "смотрели": 8,
 "смотреть": 8,
 "смысле": 6,
 "сначала": 7,
 "снизошла": 8,
 "снимать": 7,
 "сноб": 4,
 "сняли": 5,
 "со": 2,
 "собака": 6,
 "собеседница": 11,
 "собой": 5,
 "совершенно": 10,
 "совершеннолетний": 16,
 "совсем": 6,
 "содовой": 7,
 "соображает": 10,
 "сообразить": 10,
 "соседним": 8,
 "сошелся": 7,
 "спала": 5,
 "спать": 5,
 "спине": 5,
 "спиртного": 9,
 "спиртное": 8,
 "спорт": 5,
 "спрашивала": 10,
 "спрашиваю": 9,
 "спрашивают": 10,
 "спросил": 7,
 "спросила": 8,
 "спросит": 7,
 "спросить": 8,
 "спросишь": 8,
 "спустился": 9,
 "сразу": 5,
 "стаканами": 9,
 "стал": 4,
 "стала": 5,
 "стали": 5,
 "стало": 5,
 "станет": 6,
 "становилось": 11,
 "становится": 10,
 "стану": 5,
 "станцевать": 10,
 "старикашки": 10,
 "старичков": 9,
 "старого": 7,
 "старое": 6,
 "старший": 7,
 "статую": 6,
 "стать": 5,
 "степени": 7,
 "стил": 4,
 "стихами": 7,
 "стихи": 5,
 "сто": 3,
 "стоила": 6,
 "стоит": 5,
 "стол": 4,
 "столиком": 8,
 "столику": 7,
 "сторк": 5,
 "стороны": 7,
 "стоят": 5,
 "стравил": 7,
 "странно": 7,
 "страховом": 9,
 "страшно": 7,
 "страшные": 8,
 "страшный": 8,
 "строить": 7,
 "стрэдлейтером": 13,
 "ступеней": 8,
 "суббота": 7,
 "сумасшедший": 11,
 "сунуть": 6,
 "сустава": 7,
 "сутенеристых": 12,
 "сходил": 6,
 "схожу": 5,
 "счет": 4,
 "сыграют": 7,
 "сыщик": 5,
 "сэр": 3,
 "сядут": 5,
 "так": 3,
 "такая": 5,
 "таки": 4,
 "такие": 5,
 "такими": 6,
 "таких": 5,
 "такого": 6,
 "такое": 5,
 "такой": 5,
 "таком": 5,
 "такси": 5,
 "такую": 5,
 "там": 3,
 "танец": 5,
 "танцев": 6,
 "танцевал": 8,
 "танцевала": 9,
 "танцевали": 9,
 "танцевать": 9,
 "танцовщица": 10,
 "танцорки": 8,
 "танцоркой": 9,
 "танцоры": 7,
 "танцует": 7,
 "танцуете": 8,
 "таскать": 7,
 "твоей": 5,
 "творится": 8,
 "твоя": 4,
 "те": 2,
 "тебе": 4,
 "тебя": 4,
 "телефону": 8,
 "темноте": 7,
 "теннис": 6,
 "теперь": 6,
 "тех": 3,
 "тип": 3,
 "типов": 5,
 "тихо": 4,
 "то": 2,
 "тобой": 5,
 "тогда": 5,
 "того": 4,
 "тоже": 4,
 "толкнет": 7,
 "толпа": 5,
 "толстячков": 10,
 "только": 6,
 "том": 3,
 "тоненькая": 9,
 "тоном": 5,
 "тормашками": 10,
 "торчат": 6,
 "тоска": 5,
 "тоскливее": 9,
 "тоскливо": 8,
 "тот": 3,
 "точно": 5,
 "тошно": 5,
 "тошнотворные": 12,
 "трезвый": 7,
 "тремя": 5,
 "три": 3,
 "тридцать": 8,
 "тринадцать": 10,
 "троим": 5,
 "трубку": 6,
 "трудно": 6,
 "туда": 4,
 "тупица": 6,
 "тупой": 5,
 "тут": 3,
 "ты": 2,
 "тычет": 5,
 "у": 1,
 "убийственно": 11,
 "уборную": 7,
 "убраться": 8,
 "уверен": 6,
 "увидел": 6,
 "увозит": 6,
 "угодно": 6,
 "удержался": 9,
 "удивительно": 11,
 "удостоверения": 13,
 "уж": 2,
 "ужасающей": 9,
 "ужасная": 7,
 "ужасно": 6,
 "ужасный": 7,
 "уже": 3,
 "ужин": 4,
 "узнал": 5,
 "узнали": 6,
 "узнают": 6,
 "уйти": 4,
 "улетают": 7,
 "улице": 5,
 "улицу": 5,
 "ума": 3,
 "умеет": 5,
 "умела": 5,
 "умер": 4,
 "умею": 4,
 "умная": 5,
 "умница": 6,
 "умной": 5,
 "умный": 5,
 "унылую": 6,
 "уродина": 7,
 "уродины": 7,
 "уродливые": 9,
 "уселся": 6,
 "услыхали": 8,
 "устал": 5,
 "уткам": 5,
 "утки": 4,
 "уток": 4,
 "утро": 4,
 "утруждайтесь": 12,
 "ухаживать": 9,
 "уходить": 7,
 "ушел": 4,
 "уши": 3,
 "ушки": 4,
 "уэзерфилд": 9,
 "ферме": 5,
 "фиби": 4,
 "фигура": 6,
 "физическом": 10,
 "фильм": 5,
 "фокусов": 7,
 "фокусы": 6,
 "форменные": 9,
 "французскую": 11,
 "хай": 3,
 "хватает": 7,
 "хватит": 6,
 "хихикать": 8,
 "ход": 3,
 "ходил": 5,
 "ходуном": 7,
 "холл": 4,
 "холла": 5,
 "холле": 5,
 "холодом": 7,
 "хорошая": 7,
 "хорошему": 8,
 "хорошенький": 11,
 "хорошенькой": 11,
 "хорошие": 7,
 "хорошо": 6,
 "хорошую": 7,
 "хотела": 6,
 "хотелось": 8,
 "хотите": 6,
 "хоть": 4,
 "хотя": 4,
 "хотят": 5,
 "хочется": 7,
 "хочу": 4,
 "худая": 5,
 "худенькая": 9,
 "хуже": 4,
 "хулиганистая": 12,
 "целовал": 7,
 "целовались": 10,
 "центральном": 11,
 "час": 3,
 "часто": 5,
 "чего": 4,
 "чем": 3,
 "чемодан": 7,
 "через": 5,
 "чересчур": 8,
 "черт": 4,
 "чертенок": 8,
 "чертовой": 8,
 "чертом": 6,
 "черту": 5,
 "чертыхаться": 11,
 "чертям": 6,
 "честное": 7,
 "честный": 7,
 "четвертом": 9,
 "четыре": 6,
 "чистую": 6,
 "читала": 6,
 "что": 3,
 "чтоб": 4,
 "чтобы": 5,
 "чувствовать": 11,
 "чувствуют": 9,
 "чудесная": 8,
 "чуть": 4,
 "чучелы": 6,
 "чушь": 4,
 "шашки": 5,
 "шелохнемся": 10,
 "шишка": 5,
 "школу": 5,
 "школы": 5,
 "шла": 3,
 "шлюховатые": 10,
 "шлюховатых": 10,
 "шляпкам": 7,
 "шляпке": 6,
 "шляпки": 6,
 "шотландской": 11,
 "шотландцем": 10,
 "шофера": 6,
 "шоферские": 9,
 "шпион": 5,
 "штат": 4,
 "штуку": 5,
 "эда": 3,
 "эль": 3,
 "эрни": 4,
 "эта": 3,
 "эти": 3,
 "этим": 4,
 "этими": 5,
 "этих": 4,
 "это": 3,
 "этого": 5,
 "этой": 4,
 "этом": 4,
 "этот": 4,
 "эту": 3,
 "эх": 2,
 "юг": 2,
 "южного": 6,
 "юмор": 4,
 "я": 1,
 "явится": 6
}